osrm/__init__.py
osrm/classes.py
osrm/enums.py
osrm/exceptions.py
osrm/responses.py
osrm_utils-1.0.1.dist-info/LICENSE
osrm_utils-1.0.1.dist-info/METADATA
osrm_utils-1.0.1.dist-info/WHEEL
osrm_utils-1.0.1.dist-info/top_level.txt
osrm_utils-1.0.1.dist-info/RECORD
